bikestats
