Metadata-Version: 1.1
Name: bikestats
Version: 1.0.4
Summary: Scrape and save information from motorcyclespecs.co.za
Home-page: https://github.com/narfman0/bikestats
Author: Jon Robison
Author-email: narfman0@gmail.com
License: LICENSE
Keywords: bike motorcycle scraper meta
Platform: UNKNOWN
Classifier: Development Status :: 4 - Beta
Classifier: License :: OSI Approved :: GNU General Public License v3 (GPLv3)
Classifier: Operating System :: OS Independent
Classifier: Programming Language :: Python
Classifier: Topic :: Software Development :: Libraries :: Python Modules
